st_autorefresh/__init__.py
st_autorefresh-0.1.0.dist-info/LICENSE
st_autorefresh-0.1.0.dist-info/METADATA
st_autorefresh-0.1.0.dist-info/WHEEL
st_autorefresh-0.1.0.dist-info/top_level.txt
st_autorefresh-0.1.0.dist-info/RECORD
